[1,0,0,[["cc.JsonAsset",["_name","json"],1]],[[0,0,1,3]],[[0,"129",{"v":"1","map":[{"id":1,"point":[{"x":1,"y":40},{"x":40,"y":40},{"x":40,"y":59},{"x":1,"y":59}]},{"id":5,"point":[{"x":1,"y":40},{"x":2,"y":39},{"x":39,"y":39},{"x":40,"y":40}]},{"id":6,"point":[{"x":2,"y":80},{"x":80,"y":80},{"x":79,"y":79},{"x":3,"y":79}]},{"id":10,"point":[{"x":39,"y":39},{"x":40,"y":40},{"x":40,"y":59},{"x":1,"y":59},{"x":1,"y":40},{"x":2,"y":39},{"x":39,"y":39}]},{"id":105,"point":{"x":18,"y":39}},{"id":13,"point":[{"x":28,"y":79},{"x":30,"y":79},{"x":30,"y":66},{"x":28,"y":66}]},{"id":13,"point":[{"x":50,"y":79},{"x":50,"y":66},{"x":52,"y":66},{"x":52,"y":79}]},{"id":13,"point":[{"x":22,"y":64},{"x":22,"y":66},{"x":58,"y":66},{"x":58,"y":64}]},{"id":101,"point":{"x":20,"y":31}},{"id":101,"point":{"x":29,"y":38}},{"id":1,"point":[{"x":16,"y":20},{"x":16,"y":22},{"x":25,"y":22},{"x":25,"y":20}]},{"id":5,"point":[{"x":16,"y":20},{"x":17,"y":19},{"x":24,"y":19},{"x":25,"y":20}]},{"id":6,"point":[{"x":49,"y":39},{"x":33,"y":39},{"x":32,"y":40},{"x":50,"y":40}]},{"id":10,"point":[{"x":24,"y":19},{"x":17,"y":19},{"x":16,"y":20},{"x":16,"y":22},{"x":25,"y":22},{"x":25,"y":20},{"x":24,"y":19}]}],"tips":[{"x":14,"y":33},{"x":11,"y":33},{"x":11,"y":32},{"x":17,"y":32},{"x":17,"y":25},{"x":24,"y":25},{"x":24,"y":32},{"x":29,"y":32},{"x":29,"y":33},{"x":27,"y":33},{"x":27,"y":39},{"x":32,"y":39},{"x":32,"y":33},{"x":29,"y":33}],"lnk":[{"x":236,"y":574},{"x":216,"y":580},{"x":193,"y":580},{"x":172,"y":580},{"x":149,"y":578},{"x":128,"y":574},{"x":102,"y":574},{"x":87,"y":587},{"x":92,"y":609},{"x":115,"y":621},{"x":135,"y":627},{"x":159,"y":627},{"x":184,"y":627},{"x":209,"y":627},{"x":232,"y":627},{"x":260,"y":627},{"x":280,"y":635},{"x":290,"y":655},{"x":298,"y":676},{"x":300,"y":699},{"x":299,"y":724},{"x":300,"y":748},{"x":312,"y":765},{"x":327,"y":778},{"x":352,"y":779},{"x":374,"y":779},{"x":396,"y":779},{"x":416,"y":773},{"x":432,"y":761},{"x":441,"y":738},{"x":449,"y":718},{"x":453,"y":696},{"x":457,"y":675},{"x":459,"y":654},{"x":476,"y":641},{"x":497,"y":641},{"x":521,"y":641},{"x":544,"y":641},{"x":567,"y":637},{"x":583,"y":624},{"x":603,"y":619},{"x":621,"y":629},{"x":640,"y":618},{"x":640,"y":595},{"x":627,"y":578},{"x":605,"y":570},{"x":583,"y":570},{"x":558,"y":570},{"x":544,"y":552},{"x":544,"y":531},{"x":544,"y":507},{"x":544,"y":485},{"x":546,"y":463},{"x":553,"y":443},{"x":560,"y":423},{"x":575,"y":409},{"x":593,"y":396},{"x":613,"y":393},{"x":637,"y":393},{"x":661,"y":397},{"x":678,"y":411},{"x":697,"y":424},{"x":711,"y":438},{"x":715,"y":463},{"x":715,"y":488},{"x":711,"y":508},{"x":698,"y":527},{"x":679,"y":537},{"x":658,"y":541},{"x":634,"y":541},{"x":613,"y":541},{"x":593,"y":538},{"x":573,"y":533},{"x":554,"y":520}]}]],0,0,[],[],[]]
